{
  "presentationId": "1Y5grj6WhFnTeD-9Flm14SBObAVp_ZPRVicrSjkgNMKI",
  "videos": [
  ],
  "psalms": [
  ],
  "passages": [
    "Philippians 4:4-8",
    "Psalm 139",
    "Psalm 37:23",
    "Psalm 11:4",
    "Job 28:24",
    "Job 31:4",
    "2 Kings 19:27",
    "Hebrews 4:13",
    "Proverbs 1:7",
    "Proverbs 2:3-5",
    "Proverbs 2:6-11",
    "1 Corinthians 2:7-13",
    "John 10:11-16",
    "1 Peter 5:4",
    "Isaiah 40:11",
    "Hebrews 13:20",
    "Matthew 25:31-46",
    "Psalm 23"
  ],
  "paradiseHymn": [
  ]
}